rsa_crypto.py
rsa_crypto-1.0.4.dist-info/LICENSE
rsa_crypto-1.0.4.dist-info/METADATA
rsa_crypto-1.0.4.dist-info/WHEEL
rsa_crypto-1.0.4.dist-info/entry_points.txt
rsa_crypto-1.0.4.dist-info/top_level.txt
rsa_crypto-1.0.4.dist-info/RECORD
