Metadata-Version: 2.1
Name: rsa-crypto
Version: 1.0.4
Summary: Encrypt and decrypt data using RSA certificates.
Home-page: https://github.com/Christophe-Gauge/rsa_crypto
Author: Christophe Gauge
Author-email: chris@videre.us
License: GNU Lesser General Public License v3 (LGPLv3)
Platform: UNKNOWN
Classifier: Development Status :: 4 - Beta
Classifier: Intended Audience :: Developers
Classifier: Topic :: Security :: Cryptography
Classifier: License :: OSI Approved :: GNU General Public License v3 (GPLv3)
Classifier: Programming Language :: Python :: 3
Classifier: Programming Language :: Python :: 3.6
Classifier: Programming Language :: Python :: 3.7
Classifier: Programming Language :: Python :: 3.8
Classifier: Programming Language :: Python :: 3.9
Requires-Python: >=3
Requires-Dist: pycryptodome
